tmark/__init__.py
tmark/latency_tracker.py
tmark-0.0.2.dist-info/LICENSE
tmark-0.0.2.dist-info/METADATA
tmark-0.0.2.dist-info/WHEEL
tmark-0.0.2.dist-info/top_level.txt
tmark-0.0.2.dist-info/RECORD
