Metadata-Version: 2.1
Name: tmark
Version: 0.0.2
Summary: Time marking package in code.
Home-page: https://github.com/OnisOris/tmark
Author: OnisOris
Author-email: onisoris@yandex.ru
Project-URL: GitHub, https://github.com/OnisOris/tmark
Keywords: time marks plot
Classifier: Programming Language :: Python :: 3.12
Classifier: License :: OSI Approved :: GNU General Public License v2 (GPLv2)
Classifier: Operating System :: OS Independent
Requires-Python: >=3.10
License-File: LICENSE
Requires-Dist: matplotlib
Requires-Dist: numpy
Requires-Dist: pandas
